redisbloom/__init__.py
redisbloom/client.py
redisbloom_py-0.4.1.dist-info/LICENSE
redisbloom_py-0.4.1.dist-info/WHEEL
redisbloom_py-0.4.1.dist-info/METADATA
redisbloom_py-0.4.1.dist-info/RECORD
