Metadata-Version: 2.1
Name: redisbloom-py
Version: 0.4.1
Summary: RedisBloom Python Client
License: BSD-3-Clause
Keywords: Redis,Extension,Probabilistic,TopK,Cuckoo-Filter,Bloom-Filter,Count-min-sketch
Author: Redis
Author-email: oss@redis.com
Requires-Python: >=3.6,<4.0
Classifier: Development Status :: 5 - Production/Stable
Classifier: Intended Audience :: Developers
Classifier: License :: OSI Approved :: BSD License
Classifier: Programming Language :: Python
Classifier: Programming Language :: Python :: 3
Classifier: Programming Language :: Python :: 3.10
Classifier: Programming Language :: Python :: 3.6
Classifier: Programming Language :: Python :: 3.7
Classifier: Programming Language :: Python :: 3.8
Classifier: Programming Language :: Python :: 3.9
Classifier: Topic :: Database
Requires-Dist: hiredis (>=2.0.0,<3.0.0)
Requires-Dist: redis (==3.5.3)
Requires-Dist: rmtest (>=0.7.0,<0.8.0)
Requires-Dist: six (>=1.16.0,<2.0.0)
Project-URL: repository, https://github.com/RedisBloom/redisbloom-py
Project-URL: url, https://redisbloom.io
